{"version":3,"kind":"Article","sha256":"e2eff4eda9acf0a30a2cd1c8dce37530b234eb3844565fc41fc7c718507afab8","slug":"blog","location":"/pages/blog.md","dependencies":[],"frontmatter":{"title":"Blog","authors":[{"nameParsed":{"literal":"Jubílio Filiano Maússe","given":"Jubílio Filiano","family":"Maússe"},"name":"Jubílio Filiano Maússe","email":"jubiliomausse5@gmail.com","github":"Jubilio","id":"contributors-Users\\IMPACT - DBO\\OneDrive - ACTED\\Documentos\\portifolio\\MyST_Mausse\\myst-generated-uid-0","corresponding":true}],"license":{"content":{"id":"CC-BY-4.0","url":"https://creativecommons.org/licenses/by/4.0/","name":"Creative Commons Attribution 4.0 International","free":true,"CC":true}},"github":"https://github.com/Jubilio","keywords":["GIS","Remote Sensing","MEAL","Moçambique","Humanitarian","Data Analysis","ArcGIS","QGIS"],"exports":[{"format":"md","filename":"blog.md","url":"/blog-fcc5f92dfa172aa79a7b408163a30489.md"}]},"mdast":{"type":"root","children":[{"type":"block","children":[{"type":"heading","depth":2,"position":{"start":{"line":5,"column":1},"end":{"line":5,"column":1}},"children":[{"type":"text","value":"📰 Blog & Notícias","position":{"start":{"line":5,"column":1},"end":{"line":5,"column":1}},"key":"fbpu15T6Eq"}],"identifier":"id-blog-not-cias","label":"📰 Blog & Notícias","html_id":"id-blog-not-cias","implicit":true,"key":"Dynp4FJfKN"},{"type":"paragraph","position":{"start":{"line":7,"column":1},"end":{"line":7,"column":1}},"children":[{"type":"text","value":"Esta secção contém reflexões curtas, atualizações sobre missões de terreno e pensamentos soltos sobre a aplicação de tecnologias GIS no setor humanitário.","position":{"start":{"line":7,"column":1},"end":{"line":7,"column":1}},"key":"nbmJVbCLxh"}],"key":"xfAitKGhYx"},{"type":"paragraph","position":{"start":{"line":9,"column":1},"end":{"line":9,"column":1}},"children":[{"type":"link","url":"../rss.xml","position":{"start":{"line":9,"column":1},"end":{"line":9,"column":1}},"children":[{"type":"text","value":"Assinar o Feed RSS","position":{"start":{"line":9,"column":1},"end":{"line":9,"column":1}},"key":"BhizAqJda9"}],"urlSource":"../rss.xml","key":"TUyzf2ah2h"}],"key":"VjUj9CUfer"},{"type":"heading","depth":3,"position":{"start":{"line":11,"column":1},"end":{"line":11,"column":1}},"children":[{"type":"text","value":"Artigos Recentes","position":{"start":{"line":11,"column":1},"end":{"line":11,"column":1}},"key":"lQLk8nKaNa"}],"identifier":"artigos-recentes","label":"Artigos Recentes","html_id":"artigos-recentes","implicit":true,"key":"TZmkxRPinZ"},{"type":"grid","columns":[1,1,2,2],"children":[{"type":"card","children":[{"type":"cardTitle","children":[{"type":"text","value":"Primeiro Post do Blog: GIS e Acção Humanitária","position":{"start":{"line":15,"column":1},"end":{"line":15,"column":1}},"key":"L6QZXJ0mN1"}],"key":"U9pqDALFob"},{"type":"paragraph","position":{"start":{"line":16,"column":1},"end":{"line":16,"column":1}},"children":[{"type":"strong","position":{"start":{"line":16,"column":1},"end":{"line":16,"column":1}},"children":[{"type":"text","value":"Data:","position":{"start":{"line":16,"column":1},"end":{"line":16,"column":1}},"key":"yP89SOD7Bw"}],"key":"fdSYRMkNsz"},{"type":"text","value":" 30 Junho 2026","position":{"start":{"line":16,"column":1},"end":{"line":16,"column":1}},"key":"NHhTFWUsdX"}],"key":"da9vEPCiNX"},{"type":"paragraph","position":{"start":{"line":18,"column":1},"end":{"line":18,"column":1}},"children":[{"type":"text","value":"Bem-vindo ao meu novo site! Aqui irei detalhar as minhas experiências com Avaliações Rápidas de Necessidades (RNA) e muito mais.","position":{"start":{"line":18,"column":1},"end":{"line":18,"column":1}},"key":"yksTwMVH5b"}],"key":"GAliAr4Hmu"},{"type":"footer","children":[{"type":"paragraph","position":{"start":{"line":21,"column":1},"end":{"line":21,"column":1}},"children":[{"type":"link","url":"/primeiro-post","position":{"start":{"line":21,"column":1},"end":{"line":21,"column":1}},"children":[{"type":"text","value":"Ler mais","position":{"start":{"line":21,"column":1},"end":{"line":21,"column":1}},"key":"p6B8Bp6nAo"}],"urlSource":"../blog/primeiro-post.md","dataUrl":"/primeiro-post.json","internal":true,"protocol":"file","key":"tk8NI9lbs9"}],"key":"YXox5XlFTp"}],"key":"QHIkrDAfTh"}],"key":"UqU0xDxflv"}],"key":"tCMaDj773M"}],"key":"KuhwRjF0YI"}],"key":"h6f5E8VImc"},"references":{"cite":{"order":[],"data":{}}}}